bundleb2b_api_management/__init__.py
bundleb2b_api_management/company/__init__.py
bundleb2b_api_management/company/company.py
bundleb2b_api_management/dataclass_functions/__init__.py
bundleb2b_api_management/settings.py
bundleb2b_api_management/user/__init__.py
bundleb2b_api_management/user/user.py
bundleb2b_api_management-0.1.0.dist-info/METADATA
bundleb2b_api_management-0.1.0.dist-info/WHEEL
bundleb2b_api_management-0.1.0.dist-info/RECORD
