Metadata-Version: 2.1
Name: bundleb2b-api-management
Version: 0.1.0
Summary: 
Author: Craig Novak
Author-email: craig.novak@coedistributing.com
Requires-Python: >=3.10,<4.0
Classifier: Programming Language :: Python :: 3
Classifier: Programming Language :: Python :: 3.10
Classifier: Programming Language :: Python :: 3.11
Requires-Dist: requests (>=2.28.2,<3.0.0)
Requires-Dist: retry (>=0.9.2,<0.10.0)
